runhouse/main.py
runhouse/process_commands.py
runhouse/redis/database.json
runhouse/redis/db_api.py
runhouse/scripts/training_script.py
runhouse/shell_handler.py
runhouse/ssh_manager.py
runhouse/utils/utils.py
runhouse-0.1.1.dist-info/entry_points.txt
runhouse-0.1.1.dist-info/WHEEL
runhouse-0.1.1.dist-info/METADATA
runhouse-0.1.1.dist-info/RECORD
