Metadata-Version: 2.1
Name: runhouse
Version: 0.1.1
Summary: Runhouse CLI and Python Package
Author: Josh Lewittes
Author-email: josh.lewittes@gmail.com
Requires-Python: >=3.7,<4.0
Classifier: Programming Language :: Python :: 3
Classifier: Programming Language :: Python :: 3.10
Classifier: Programming Language :: Python :: 3.7
Classifier: Programming Language :: Python :: 3.8
Classifier: Programming Language :: Python :: 3.9
Requires-Dist: PyNaCl (==1.5.0)
Requires-Dist: PyYAML (==6.0)
Requires-Dist: attrs (==21.4.0)
Requires-Dist: bcrypt (==3.2.2)
Requires-Dist: boto3 (==1.23.0)
Requires-Dist: botocore (==1.26.0)
Requires-Dist: cachetools (==5.0.0)
Requires-Dist: certifi (==2021.10.8)
Requires-Dist: cffi (==1.15.0)
Requires-Dist: charset-normalizer (==2.0.12)
Requires-Dist: click (==7.1.2)
Requires-Dist: colorama (==0.4.4)
Requires-Dist: cryptography (==37.0.2)
Requires-Dist: google-auth (==2.6.6)
Requires-Dist: idna (==3.3)
Requires-Dist: importlib-metadata (==4.11.3)
Requires-Dist: iniconfig (==1.1.1)
Requires-Dist: jmespath (==1.0.0)
Requires-Dist: kubernetes (==23.6.0)
Requires-Dist: oauthlib (==3.2.0)
Requires-Dist: packaging (==21.3)
Requires-Dist: paramiko (==2.10.4)
Requires-Dist: pluggy (==0.13.1)
Requires-Dist: py (==1.11.0)
Requires-Dist: pyasn1 (==0.4.8)
Requires-Dist: pyasn1-modules (==0.2.8)
Requires-Dist: pycparser (==2.21)
Requires-Dist: pyparsing (==3.0.8)
Requires-Dist: python-dateutil (==2.8.2)
Requires-Dist: python-dotenv (==0.20.0)
Requires-Dist: requests (==2.27.1)
Requires-Dist: requests-oauthlib (==1.3.1)
Requires-Dist: rsa (==4.8)
Requires-Dist: s3transfer (==0.5.2)
Requires-Dist: shellingham (==1.4.0)
Requires-Dist: typer[all] (>=0.4.1,<0.5.0)
Requires-Dist: typing-extensions (==4.2.0)
Requires-Dist: urllib3 (==1.26.9)
Requires-Dist: websocket-client (==1.3.2)
Requires-Dist: zipp (==3.8.0)
